<?xml version="1.0" encoding="UTF-8"?>
<!-- vim:fdl=1:
-->
<!-- Template for Print preview -->
<templates id="template" xml:space="preserve">
    <t t-name="PosInvoiceTicket">
        <div class="pos-sale-ticket">
            <div class="pos-center-align">
                <t t-esc="new Date().toString(Date.CultureInfo.formatPatterns.shortDate + ' ' + Date.CultureInfo.formatPatterns.longTime)"/>. Invoice <t t-esc="order.get_invoice_name()"/>
                <hr />
                <b class="emph"><t t-esc="widget.pos.company.name"/></b><br />
                <t t-if="widget.pos.company.vat">
                    <b class="emph"><t t-esc="widget.pos.company.vat"/></b><br />
                </t>
                <t t-if="widget.pos.company.street">
                    <b><t t-esc="widget.pos.company.street"/></b><br />
                </t>
                <t t-if="widget.pos.company.city">
                    <b><t t-esc="widget.pos.company.city || ''"/> <t t-esc="widget.pos.company.zip || ''"/></b><br />
                </t>
                <t t-if="widget.pos.company.phone">
                    <t t-esc="widget.pos.company.phone"/><br />
                </t>
                <t t-if="widget.pos.config.receipt_header">
                    <br />
                    <div style='text-align:center'>
                        <t t-esc="widget.pos.config.receipt_header" />
                    </div>
                </t>
                <br />
            </div>
            <div>
                <b>Client:</b> <t t-esc="order.get_client_name()"/><br />
                <b>Address:</b> <t t-esc="order.get_client().address || ''"/><br />
                <b>Phone:</b> <t t-esc="order.get_client().phone || 'n/a'"/><br />
                <br />
            </div>
            <table>
                <colgroup>
                    <col width='45%' />
                    <col width='10%' />
                    <col width='20%' />
                    <col width='25%' />
                </colgroup>
                <thead class="pos-table-header">
                    <tr>
                        <th style="text-decoration: underline;">Description</th>
                        <th style="text-decoration: underline;">Tax</th>
                        <th class="pos-right-align" style="text-decoration: underline;">Quantity</th>
                        <th class="pos-right-align" style="text-decoration: underline;">Price</th>
                    </tr>
                </thead>
                <tbody>
                    <tr t-foreach="orderlines" t-as="orderline">
                        <td>
                            <t t-esc="orderline.get_product().display_name"/>
                            <t t-if="orderline.get_discount() > 0">
                                <div class="pos-disc-font">
                                    With a <t t-esc="orderline.get_discount()"/>% discount
                                </div>
                            </t>
                        </td>
                        <td>
                            <t t-foreach="orderline.get_applicable_taxes()" t-as="linetax">
                                <t t-esc="linetax.name"/>
                            </t>
                        </td>
                        <td class="pos-right-align">
                            <t t-esc="orderline.get_quantity_str_with_unit()"/>
                        </td>
                        <td class="pos-right-align">
                            <t t-esc="widget.format_currency(orderline.get_display_price())"/>
                        </td>
                    </tr>
                </tbody>
            </table>
            <br />
            <table>
                <tr>
                    <td>Subtotal:</td>
                    <td class="pos-right-align">
                        <t t-esc="widget.format_currency(order.getSubtotal())"/>
                    </td>
                </tr>
                <t t-foreach="order.getTaxDetails()" t-as="taxdetail">
                    <tr>
                        <td><t t-esc="taxdetail.tax.name" /></td>
                        <td class="pos-right-align">
                            <t t-esc="widget.format_currency(taxdetail.amount)" />
                        </td>
                    </tr>
                </t>
                <tr>
                    <td>Discount:</td>
                    <td class="pos-right-align">
                        <t t-esc="widget.format_currency(order.getDiscountTotal())"/>
                    </td>
                </tr>
                <tr class="emph">
                    <td>Total:</td>
                    <td class="pos-right-align">
                        <t t-esc="widget.format_currency(order.getTotalTaxIncluded())"/>
                    </td>
                </tr>
            </table>
            <br />
            <table>
                <tr t-foreach="paymentlines" t-as="line">
                    <td>
                        <t t-esc="line.name"/>
                    </td>
                    <td class="pos-right-align">
                        <t t-esc="widget.format_currency(line.get_amount())"/>
                    </td>
                </tr>
            </table>
            <br />
            <table>
                <tr><td>Change:</td><td class="pos-right-align">
                <t t-esc="widget.format_currency(order.getChange())"/>
                </td></tr>
            </table>
            <t t-if="order.get_client().employee">
                <br />
                <table>
                    <tr>
                        <td>Firma del empleado:</td>
                        <td class="pos-right-align">_________________</td>
                    </tr>
                </table>
            </t>
            <t t-if="widget.pos.config.receipt_footer">
                <hr />
                <div style='text-align:center; font-size: 10px;'>
                    <t t-esc="widget.pos.config.receipt_footer" />
                </div>
            </t>
        </div>
    </t>

    <!-- Template for proxy -->
    <t t-name="XmlInvoiceReceipt">
        <receipt align='center' width='40' value-thousands-separator='' >
            Date: <t t-esc="receipt.date.localestring"/>. Invoice <t t-esc="receipt.invoice_name"/>
            <hr />
            <t t-if='receipt.company.logo'>
                <img t-att-src='receipt.company.logo' />
                <t t-if='receipt.company.vat'>
                    <h2><t t-esc='receipt.company.vat' /></h2>
                </t>
                <br/>
            </t>
            <t t-if='!receipt.company.logo'>
                <h1><t t-esc='receipt.company.name' /></h1>
                <t t-if='receipt.company.vat'>
                    <h2><t t-esc='receipt.company.vat' /></h2>
                </t>
                <br/>
            </t>

            <div font='b'>
                <t t-if='receipt.company.contact_address'>
                    <div><t t-esc='receipt.company.contact_address' /></div>
                </t>
                <t t-if='receipt.company.phone'>
                    <div>Tel:<t t-esc='receipt.company.phone' /></div>
                </t>
                <t t-if='receipt.header'>
                    <div><t t-esc='receipt.header' /></div>
                </t>
                <t t-if='receipt.cashier'>
                    <div>--------------------------------</div>
                    <div>Served by <t t-esc='receipt.cashier' /></div>
                </t>
            </div>
            <br /><br />
            
            <div font='b'>
                <left>
                    <t t-if='receipt.client'>
                        <div>Client:<t t-esc='receipt.client' /></div>
                    </t>
                    <t t-if='receipt.client_address'>
                        <div>Address:<t t-esc='receipt.client_address' /></div>
                    </t>
                    <t t-if='receipt.client_phone'>
                        <div>Phone:<t t-esc='receipt.client_phone' /></div>
                    </t>
                </left>
            </div>
            <br /><br />

            <!-- Orderlines -->

            <div line-ratio='0.6'>
                <t t-foreach='receipt.orderlines' t-as='line'>
                    <t t-set='simple' t-value='line.discount === 0 and line.unit_name === "Unit(s)" and line.quantity === 1' />
                    <t t-if='simple'>
                        <line>
                            <left><t t-esc='line.product_name' /></left>
                            <right><value><t t-esc='line.price_display' /></value></right>
                        </line>
                    </t>
                    <t t-if='!simple'>
                        <line><left><t t-esc='line.product_name' /></left></line>
                        <t t-if='line.discount !== 0'>
                            <line indent='1'><left>Discount: <t t-esc='line.discount' />%</left></line>
                        </t>
                        <line indent='1'>
                            <left>
                                <value value-decimals='3' value-autoint='on'>
                                    <t t-esc='line.quantity' />
                                </value>
                                <t t-if='line.unit_name !== "Unit(s)"'>
                                    <t t-esc='line.unit_name' /> 
                                </t>
                                x 
                                <value value-decimals='2'>
                                    <t t-esc='line.price' />
                                </value>
                            </left>
                            <right>
                                <value><t t-esc='line.price_display' /></value>
                            </right>
                        </line>
                    </t>
                </t>
            </div>

            <!-- Subtotal -->

            <t t-set='taxincluded' t-value='Math.abs(receipt.subtotal - receipt.total_with_tax) &lt;= 0.000001' />
            <t t-if='!taxincluded'>
                <line><right>--------</right></line>
                <line><left>Subtotal</left><right> <value><t t-esc="receipt.subtotal" /></value></right></line>
                <t t-foreach='receipt.tax_details' t-as='tax'>
                    <line>
                        <left><t t-esc='tax.name' /></left>
                        <right><value><t t-esc='tax.amount' /></value></right>
                    </line>
                </t>
            </t>

            <!-- Total -->

            <line><right>--------</right></line>
            <line size='double-height'>
                <left><pre>        TOTAL</pre></left>
                <right><value><t t-esc='receipt.total_with_tax' /></value></right>
            </line>
            <br/><br/>

            <!-- Payment Lines -->

            <t t-foreach='receipt.paymentlines' t-as='line'>
                <line>
                    <left><t t-esc='line.journal' /></left>
                    <right><value><t t-esc='line.amount'/></value></right>
                </line>
            </t>
            <br/> 

            <line size='double-height'>
                <left><pre>        CHANGE</pre></left>
                <right><value><t t-esc='receipt.change' /></value></right>
            </line>
            <br/>
            
            <!-- Extra Payment Info -->

            <t t-if='receipt.total_discount'>
                <line>
                    <left>Discounts</left>
                    <right><value><t t-esc='receipt.total_discount'/></value></right>
                </line>
            </t>
            <t t-if='taxincluded'>
                <t t-foreach='receipt.tax_details' t-as='tax'>
                    <line>
                        <left><t t-esc='tax.name' /></left>
                        <right><value><t t-esc='tax.amount' /></value></right>
                    </line>
                </t>
            </t>
            <t t-if='receipt.client_employee'>
                <line>
                    <left>Firma del empleado:</left>
                    <right>____________________________</right>
                </line>
            </t>

            <!-- Footer -->
            <t t-if='receipt.footer'>
                <br/>
                <pre><t t-esc='receipt.footer' /></pre>
                <br/>
                <br/>
            </t>

            <br/>
            <div font='b'>
                <div><t t-esc='receipt.name' /></div>
                <div><t t-esc='receipt.date.localestring' /></div>
            </div>

        </receipt>
    </t>
</templates>